pykrak/__init__.py
pykrak/adia_model.py
pykrak/adia_modes.py
pykrak/adjoint.py
pykrak/attn_pert.py
pykrak/cm_model.py
pykrak/coupled_modes.py
pykrak/env_pert.py
pykrak/env_test.py
pykrak/envs.py
pykrak/group_pert.py
pykrak/inverse_iteration.py
pykrak/likelihoods.py
pykrak/linearized_model.py
pykrak/mesh_routines.py
pykrak/mf_model.py
pykrak/misc.py
pykrak/node_model.py
pykrak/pekeris_test.py
pykrak/pressure_calc.py
pykrak/pykrak_env.py
pykrak/range_dep_model.py
pykrak/raw_pykrak.py
pykrak/setup.py
pykrak/shooting_routines.py
pykrak/sturm_seq.py
pykrak/swell_pert.py
pykrak/test_helpers.py
pykrak/wave_helpers.py
pykrak/wave_inverse_iteration.py
pykrak/wave_mesh_routines.py
pykrak/wave_sturm_seq.py
pykrak-2.0.4.dist-info/LICENSE
pykrak-2.0.4.dist-info/METADATA
pykrak-2.0.4.dist-info/WHEEL
pykrak-2.0.4.dist-info/top_level.txt
pykrak-2.0.4.dist-info/RECORD
